soft_moe/__init__.py
soft_moe/soft_moe.py
soft_moe/vision_transformer.py
tests/__init__.py
tests/test_soft_moe.py
tests/test_vision_transformer.py
soft_moe-0.0.1.dist-info/LICENSE
soft_moe-0.0.1.dist-info/METADATA
soft_moe-0.0.1.dist-info/WHEEL
soft_moe-0.0.1.dist-info/top_level.txt
soft_moe-0.0.1.dist-info/RECORD
