Metadata-Version: 2.1
Name: soft-moe
Version: 0.0.1
Summary: PyTorch implementation of 'From Sparse to Soft Mixtures of Experts'
Home-page: https://github.com/bwconrad/soft-moe
Author: Ben Conrad
Author-email: benwconrad@proton.me
License: Apache-2.0
Keywords: transformers,artificial intelligence,computer vision,deep learning
Classifier: Intended Audience :: Developers
Classifier: Intended Audience :: Science/Research
Classifier: Topic :: Scientific/Engineering :: Artificial Intelligence
Classifier: License :: OSI Approved :: Apache Software License
Classifier: Programming Language :: Python :: 3.10
Classifier: Programming Language :: Python :: 3.11
Requires-Python: >=3.10
License-File: LICENSE
Requires-Dist: timm (>=0.9.2)
Requires-Dist: torch (>=2.0.1)
